zish/__init__.py
zish/core.py
zish/antlr/ZishLexer.py
zish/antlr/ZishListener.py
zish/antlr/ZishParser.py
zish/antlr/__init__.py
zish_antlr-0.0.14.dist-info/LICENSE
zish_antlr-0.0.14.dist-info/METADATA
zish_antlr-0.0.14.dist-info/WHEEL
zish_antlr-0.0.14.dist-info/top_level.txt
zish_antlr-0.0.14.dist-info/RECORD
