Metadata-Version: 2.1
Name: zish-antlr
Version: 0.0.14
Summary: A Python library for the Zish format using ANTLR.
License: MIT No Attribution
Project-URL: Homepage, https://github.com/tlocke/zish_python_antlr
Keywords: zish,antlr
Classifier: Development Status :: 5 - Production/Stable
Classifier: Intended Audience :: Developers
Classifier: License :: OSI Approved :: MIT No Attribution License (MIT-0)
Classifier: Programming Language :: Python
Classifier: Programming Language :: Python :: 3
Classifier: Programming Language :: Python :: 3.7
Classifier: Programming Language :: Python :: 3.8
Classifier: Programming Language :: Python :: 3.9
Classifier: Programming Language :: Python :: 3.10
Classifier: Programming Language :: Python :: Implementation
Classifier: Programming Language :: Python :: Implementation :: CPython
Classifier: Programming Language :: Python :: Implementation :: PyPy
Classifier: Operating System :: OS Independent
Requires-Python: >=3.7
License-File: LICENSE
Requires-Dist: antlr4-python3-runtime (==4.11.1)
Requires-Dist: arrow (>=1.2.3)
Requires-Dist: importlib-metadata (>=1.0) ; python_version < "3.8"
